{
    "state_membership_history": [
        {
            "L1": 0.9,
            "L2": 0,
            "M1": 0.1,
            "H1": 0.01
        },
        {
            "L1": 0.09028098099999993,
            "L2": 0.0,
            "M1": 0.8943393992147524,
            "H1": 0.34605910141413987
        },
        {
            "L1": 0.0999580448226699,
            "L2": 0.0,
            "M1": 0.2144801375765626,
            "H1": 0.9388615352270325
        },
        {
            "L1": 0.039355884312804235,
            "L2": 0.0,
            "M1": 0.2059083885596269,
            "H1": 0.8979270798923368
        },
        {
            "L1": 0.032823165210045246,
            "L2": 0.0,
            "M1": 0.14728870603871402,
            "H1": 0.8702753796352691
        },
        {
            "L1": 0.02618868718719225,
            "L2": 0.0,
            "M1": 0.1327083047501879,
            "H1": 0.8408274053866005
        },
        {
            "L1": 0.8692827850216482,
            "L2": 0.0,
            "M1": 0.24173789244297905,
            "H1": 0.23644557682563516
        },
        {
            "L1": 0.8546211998041988,
            "L2": 0.0,
            "M1": 0.10064324692089588,
            "H1": 0.34824311165219235
        },
        {
            "L1": 0.8456365844609492,
            "L2": 0.0,
            "M1": 0.12771142094907717,
            "H1": 0.3370542312846663
        },
        {
            "L1": 0.10943139066558638,
            "L2": 0.0,
            "M1": 0.3303755889688752,
            "H1": 0.9149866131256643
        },
        {
            "L1": 0.12622885898005076,
            "L2": 0.0,
            "M1": 0.09256393765274806,
            "H1": 0.88660952625787
        }
    ],
    "blocking_history": [
        {
            "B": 0.10144890101269854,
            "C": 0.9300454334208009
        },
        {
            "B": 0.419888250175284,
            "C": 0.9254885881486761
        },
        {
            "B": 0.8658333063365165,
            "C": 0.4196380155173497
        },
        {
            "B": 0.8335518057404425,
            "C": 0.3572364782861267
        },
        {
            "B": 0.810628471595731,
            "C": 0.2901058218368169
        },
        {
            "B": 0.22530210935847328,
            "C": 0.9023078283603619
        },
        {
            "B": 0.7594198700866853,
            "C": 0.6457915192904156
        },
        {
            "B": 0.7554643668775542,
            "C": 0.6349600330892023
        },
        {
            "B": 0.39126833857105947,
            "C": 0.9167162852354376
        },
        {
            "B": 0.8084927066696891,
            "C": 0.5305330943151416
        }
    ]
}