{
    "Dominant Error State Check": [
        {
            "Step": 0,
            "Action": "Select_file",
            "FMMFSM State": "Folder_pri",
            "Result": "True"
        },
        {
            "Step": 1,
            "Action": "Select_file",
            "FMMFSM State": "File_pri",
            "Result": "True"
        },
        {
            "Step": 2,
            "Action": "Select_file",
            "FMMFSM State": "File_pri",
            "Result": "True"
        },
        {
            "Step": 3,
            "Action": "Select_file",
            "FMMFSM State": "File_pri",
            "Result": "True"
        },
        {
            "Step": 4,
            "Action": "Select_file",
            "FMMFSM State": "File_pri",
            "Result": "True"
        },
        {
            "Step": 5,
            "Action": "Toggle",
            "FMMFSM State": "File_pri",
            "Result": "True"
        },
        {
            "Step": 6,
            "Action": "Toggle",
            "FMMFSM State": "Folder_pub",
            "Result": "False",
            "Fuzzy Max State": {
                "Folder_pub": 0.6578961455775594
            },
            "Binary True State": {
                "File_pub": 0.04349427499205294
            }
        },
        {
            "Step": 7,
            "Action": "Select_file",
            "FMMFSM State": "Folder_pri",
            "Result": "False",
            "Fuzzy Max State": {
                "Folder_pri": 0.6121417715625506
            },
            "Binary True State": {
                "File_pri": 0.0195735743963934
            }
        },
        {
            "Step": 8,
            "Action": "Select_file",
            "FMMFSM State": "File_pri",
            "Result": "True"
        },
        {
            "Step": 9,
            "Action": "Select_folder",
            "FMMFSM State": "File_pri",
            "Result": "True"
        },
        {
            "Step": 10,
            "Action": "Select_folder",
            "FMMFSM State": "Folder_pri",
            "Result": "True"
        },
        {
            "Step": 11,
            "Action": "Select_file",
            "FMMFSM State": "Folder_pri",
            "Result": "True"
        },
        {
            "Step": 12,
            "Action": "Toggle",
            "FMMFSM State": "File_pri",
            "Result": "True"
        },
        {
            "Step": 13,
            "Action": "Toggle",
            "FMMFSM State": "Folder_pub",
            "Result": "False",
            "Fuzzy Max State": {
                "Folder_pub": 0.6470800014650535
            },
            "Binary True State": {
                "File_pub": 0.046716026918141806
            }
        },
        {
            "Step": 14,
            "Action": "Select_file",
            "FMMFSM State": "Folder_pri",
            "Result": "False",
            "Fuzzy Max State": {
                "Folder_pri": 0.6068733120989704
            },
            "Binary True State": {
                "File_pri": 0.02117314243119428
            }
        },
        {
            "Step": 15,
            "Action": "Select_file",
            "FMMFSM State": "File_pri",
            "Result": "True"
        },
        {
            "Step": 16,
            "Action": "Select_folder",
            "FMMFSM State": "File_pri",
            "Result": "True"
        },
        {
            "Step": 17,
            "Action": "Select_folder",
            "FMMFSM State": "Folder_pri",
            "Result": "True"
        },
        {
            "Step": 18,
            "Action": "Toggle",
            "FMMFSM State": "Folder_pri",
            "Result": "True"
        },
        {
            "Step": 19,
            "Action": "Select_folder",
            "FMMFSM State": "Folder_pub",
            "Result": "True"
        },
        {
            "Step": 20,
            "Action": null,
            "FMMFSM State": "Folder_pub",
            "Result": "True"
        }
    ],
    "Nondeterministic Confusion Check": [
        {
            "Step": 11,
            "Action": "Select_file",
            "FMMFSM State": "Folder_pri",
            "States": {
                "Folder_pri": 0.8051324313671591,
                "Folder_pub": 0.7800165156178018
            }
        },
        {
            "Step": 12,
            "Action": "Toggle",
            "FMMFSM State": "File_pri",
            "States": {
                "File_pri": 0.8462744977248412,
                "File_pub": 0.8321279977337869
            }
        },
        {
            "Step": 13,
            "Action": "Toggle",
            "FMMFSM State": "Folder_pub",
            "States": {
                "Folder_pri": 0.6367352566044362,
                "Folder_pub": 0.6470800014650535
            }
        },
        {
            "Step": 14,
            "Action": "Select_file",
            "FMMFSM State": "Folder_pri",
            "States": {
                "Folder_pri": 0.6068733120989704,
                "Folder_pub": 0.5988033068496373
            }
        },
        {
            "Step": 15,
            "Action": "Select_file",
            "FMMFSM State": "File_pri",
            "States": {
                "File_pri": 0.5029845050786916,
                "File_pub": 0.4972952613916375
            }
        },
        {
            "Step": 16,
            "Action": "Select_folder",
            "FMMFSM State": "File_pri",
            "States": {
                "File_pri": 0.6415532743562691,
                "File_pub": 0.6366218441231832
            }
        },
        {
            "Step": 17,
            "Action": "Select_folder",
            "FMMFSM State": "Folder_pri",
            "States": {
                "Folder_pri": 0.72069286610541,
                "Folder_pub": 0.7171047427049368
            }
        },
        {
            "Step": 18,
            "Action": "Toggle",
            "FMMFSM State": "Folder_pri",
            "States": {
                "Folder_pri": 0.8050304082164464,
                "Folder_pub": 0.8027271773381768
            }
        },
        {
            "Step": 19,
            "Action": "Select_folder",
            "FMMFSM State": "Folder_pub",
            "States": {
                "Folder_pri": 0.7455423546511066,
                "Folder_pub": 0.7473013323019702
            }
        },
        {
            "Step": 20,
            "Action": null,
            "FMMFSM State": "Folder_pub",
            "States": {
                "Folder_pri": 0.6673521788655796,
                "Folder_pub": 0.6686210823272829
            }
        }
    ]
}