{
    "Dominant State Error": [
        {
            "Step": 0,
            "Action": "Toggle",
            "FMMFSM State": "Folder_pri",
            "Result": "True"
        },
        {
            "Step": 1,
            "Action": "Select_folder",
            "FMMFSM State": "Folder_pub",
            "Result": "True"
        },
        {
            "Step": 2,
            "Action": "Select_file",
            "FMMFSM State": "Folder_pub",
            "Result": "True"
        },
        {
            "Step": 3,
            "Action": "Select_file",
            "FMMFSM State": "File_pub",
            "Result": "True"
        },
        {
            "Step": 4,
            "Action": "Select_file",
            "FMMFSM State": "File_pub",
            "Result": "True"
        },
        {
            "Step": 5,
            "Action": "Toggle",
            "FMMFSM State": "File_pub",
            "Result": "True"
        },
        {
            "Step": 6,
            "Action": "Toggle",
            "FMMFSM State": "File_pub",
            "Result": "False",
            "Fuzzy Max State": {
                "File_pub": 0.8543631935906577
            },
            "Binary True State": {
                "File_pri": 0.8320507269971884
            }
        },
        {
            "Step": 7,
            "Action": "Toggle",
            "FMMFSM State": "File_pub",
            "Result": "True"
        },
        {
            "Step": 8,
            "Action": "Toggle",
            "FMMFSM State": "File_pub",
            "Result": "False",
            "Fuzzy Max State": {
                "File_pub": 0.8488036638101311
            },
            "Binary True State": {
                "File_pri": 0.8285139808745624
            }
        },
        {
            "Step": 9,
            "Action": "Toggle",
            "FMMFSM State": "File_pub",
            "Result": "True"
        },
        {
            "Step": 10,
            "Action": "Select_folder",
            "FMMFSM State": "File_pub",
            "Result": "False",
            "Fuzzy Max State": {
                "File_pub": 0.8432776850777355
            },
            "Binary True State": {
                "File_pri": 0.8247676388950184
            }
        },
        {
            "Step": 11,
            "Action": "Select_folder",
            "FMMFSM State": "Folder_pub",
            "Result": "False",
            "Fuzzy Max State": {
                "Folder_pub": 0.8166034528692228
            },
            "Binary True State": {
                "Folder_pri": 0.8117438086899346
            }
        },
        {
            "Step": 12,
            "Action": "Select_folder",
            "FMMFSM State": "Folder_pub",
            "Result": "False",
            "Fuzzy Max State": {
                "Folder_pub": 0.8640288337497914
            },
            "Binary True State": {
                "Folder_pri": 0.8613523458519767
            }
        },
        {
            "Step": 13,
            "Action": "Toggle",
            "FMMFSM State": "Folder_pub",
            "Result": "False",
            "Fuzzy Max State": {
                "Folder_pub": 0.885444540795756
            },
            "Binary True State": {
                "Folder_pri": 0.8840907549600171
            }
        },
        {
            "Step": 14,
            "Action": "Toggle",
            "FMMFSM State": "Folder_pri",
            "Result": "False",
            "Fuzzy Max State": {
                "Folder_pri": 0.813628236380874
            },
            "Binary True State": {
                "Folder_pub": 0.8125962514704597
            }
        },
        {
            "Step": 15,
            "Action": "Toggle",
            "FMMFSM State": "Folder_pub",
            "Result": "False",
            "Fuzzy Max State": {
                "Folder_pub": 0.7550645974287973
            },
            "Binary True State": {
                "Folder_pri": 0.7542729260052357
            }
        },
        {
            "Step": 16,
            "Action": "Toggle",
            "FMMFSM State": "File_pub",
            "Result": "False",
            "Fuzzy Max State": {
                "File_pub": 0.743816035342971
            },
            "Binary True State": {
                "Folder_pub": 0.7059867068693084
            }
        },
        {
            "Step": 17,
            "Action": "Toggle",
            "FMMFSM State": "File_pub",
            "Result": "False",
            "Fuzzy Max State": {
                "File_pub": 0.7463185872252807
            },
            "Binary True State": {
                "Folder_pri": 0.6655177456687014
            }
        },
        {
            "Step": 18,
            "Action": "Toggle",
            "FMMFSM State": "File_pub",
            "Result": "False",
            "Fuzzy Max State": {
                "File_pub": 0.7484004016926721
            },
            "Binary True State": {
                "Folder_pub": 0.6312686246266523
            }
        },
        {
            "Step": 19,
            "Action": "Toggle",
            "FMMFSM State": "File_pub",
            "Result": "False",
            "Fuzzy Max State": {
                "File_pub": 0.7501295578323768
            },
            "Binary True State": {
                "Folder_pri": 0.6020333315548978
            }
        },
        {
            "Step": 20,
            "Action": null,
            "FMMFSM State": "File_pub",
            "Result": "False",
            "Fuzzy Max State": {
                "File_pub": 0.7515644860268503
            },
            "Binary True State": {
                "Folder_pub": 0.5769101753193007
            }
        }
    ],
    "Threshold State Error": [
        {
            "Step": 0,
            "Action": "Toggle",
            "FMMFSM State": "Folder_pri",
            "Result": "True"
        },
        {
            "Step": 1,
            "Action": "Select_folder",
            "FMMFSM State": "Folder_pub",
            "Result": "True"
        },
        {
            "Step": 2,
            "Action": "Select_file",
            "FMMFSM State": "Folder_pub",
            "Result": "False",
            "Fuzzy Above Threshold": "No state above threshold"
        },
        {
            "Step": 3,
            "Action": "Select_file",
            "FMMFSM State": "File_pub",
            "Result": "True"
        },
        {
            "Step": 4,
            "Action": "Select_file",
            "FMMFSM State": "File_pub",
            "Result": "True"
        },
        {
            "Step": 5,
            "Action": "Toggle",
            "FMMFSM State": "File_pub",
            "Result": "True"
        },
        {
            "Step": 6,
            "Action": "Toggle",
            "FMMFSM State": "File_pub",
            "Result": "True"
        },
        {
            "Step": 7,
            "Action": "Toggle",
            "FMMFSM State": "File_pub",
            "Result": "True"
        },
        {
            "Step": 8,
            "Action": "Toggle",
            "FMMFSM State": "File_pub",
            "Result": "True"
        },
        {
            "Step": 9,
            "Action": "Toggle",
            "FMMFSM State": "File_pub",
            "Result": "True"
        },
        {
            "Step": 10,
            "Action": "Select_folder",
            "FMMFSM State": "File_pub",
            "Result": "True"
        },
        {
            "Step": 11,
            "Action": "Select_folder",
            "FMMFSM State": "Folder_pub",
            "Result": "True"
        },
        {
            "Step": 12,
            "Action": "Select_folder",
            "FMMFSM State": "Folder_pub",
            "Result": "True"
        },
        {
            "Step": 13,
            "Action": "Toggle",
            "FMMFSM State": "Folder_pub",
            "Result": "True"
        },
        {
            "Step": 14,
            "Action": "Toggle",
            "FMMFSM State": "Folder_pri",
            "Result": "True"
        },
        {
            "Step": 15,
            "Action": "Toggle",
            "FMMFSM State": "Folder_pub",
            "Result": "True"
        },
        {
            "Step": 16,
            "Action": "Toggle",
            "FMMFSM State": "File_pub",
            "Result": "True"
        }
    ],
    "Dominant Task Error": [
        {
            "Step": 6,
            "Action": "Toggle",
            "FMMFSM Task Label": "Insecure",
            "System Task Label": "Secure"
        },
        {
            "Step": 8,
            "Action": "Toggle",
            "FMMFSM Task Label": "Insecure",
            "System Task Label": "Secure"
        },
        {
            "Step": 10,
            "Action": "Select_folder",
            "FMMFSM Task Label": "Insecure",
            "System Task Label": "Secure"
        },
        {
            "Step": 11,
            "Action": "Select_folder",
            "FMMFSM Task Label": "Insecure",
            "System Task Label": "Secure"
        },
        {
            "Step": 12,
            "Action": "Select_folder",
            "FMMFSM Task Label": "Insecure",
            "System Task Label": "Secure"
        },
        {
            "Step": 13,
            "Action": "Toggle",
            "FMMFSM Task Label": "Insecure",
            "System Task Label": "Secure"
        },
        {
            "Step": 14,
            "Action": "Toggle",
            "FMMFSM Task Label": "Secure",
            "System Task Label": "Insecure"
        },
        {
            "Step": 15,
            "Action": "Toggle",
            "FMMFSM Task Label": "Insecure",
            "System Task Label": "Secure"
        },
        {
            "Step": 17,
            "Action": "Toggle",
            "FMMFSM Task Label": "Insecure",
            "System Task Label": "Secure"
        },
        {
            "Step": 19,
            "Action": "Toggle",
            "FMMFSM Task Label": "Insecure",
            "System Task Label": "Secure"
        }
    ],
    "Dominant Blocking State": [
        {
            "Step": 5,
            "Action": "Toggle",
            "FMMFSM State": "File_pub"
        },
        {
            "Step": 6,
            "Action": "Toggle",
            "FMMFSM State": "File_pub"
        },
        {
            "Step": 7,
            "Action": "Toggle",
            "FMMFSM State": "File_pub"
        },
        {
            "Step": 8,
            "Action": "Toggle",
            "FMMFSM State": "File_pub"
        },
        {
            "Step": 9,
            "Action": "Toggle",
            "FMMFSM State": "File_pub"
        },
        {
            "Step": 16,
            "Action": "Toggle",
            "FMMFSM State": "File_pub"
        },
        {
            "Step": 17,
            "Action": "Toggle",
            "FMMFSM State": "File_pub"
        },
        {
            "Step": 18,
            "Action": "Toggle",
            "FMMFSM State": "File_pub"
        },
        {
            "Step": 19,
            "Action": "Toggle",
            "FMMFSM State": "File_pub"
        }
    ],
    "Dominant Blocking Task": [
        {
            "Step": 5,
            "Action": "Toggle",
            "FMMFSM State": "File_pub"
        },
        {
            "Step": 6,
            "Action": "Toggle",
            "FMMFSM State": "File_pub"
        },
        {
            "Step": 7,
            "Action": "Toggle",
            "FMMFSM State": "File_pub"
        },
        {
            "Step": 8,
            "Action": "Toggle",
            "FMMFSM State": "File_pub"
        },
        {
            "Step": 9,
            "Action": "Toggle",
            "FMMFSM State": "File_pub"
        },
        {
            "Step": 16,
            "Action": "Toggle",
            "FMMFSM State": "File_pub"
        },
        {
            "Step": 17,
            "Action": "Toggle",
            "FMMFSM State": "File_pub"
        },
        {
            "Step": 18,
            "Action": "Toggle",
            "FMMFSM State": "File_pub"
        },
        {
            "Step": 19,
            "Action": "Toggle",
            "FMMFSM State": "File_pub"
        }
    ],
    "Threshold Nondeterministic State Confusion": [
        {
            "Step": 4,
            "Action": "Select_file",
            "FMMFSM Task Labels": {
                "File_pri": 0.7764636066833672,
                "File_pub": 0.8167712107390684
            }
        },
        {
            "Step": 5,
            "Action": "Toggle",
            "FMMFSM Task Labels": {
                "File_pri": 0.8337091396642041,
                "File_pub": 0.8570991013834725
            }
        },
        {
            "Step": 6,
            "Action": "Toggle",
            "FMMFSM Task Labels": {
                "File_pri": 0.8320507269971884,
                "File_pub": 0.8543631935906577
            }
        },
        {
            "Step": 7,
            "Action": "Toggle",
            "FMMFSM Task Labels": {
                "File_pri": 0.8303324138029466,
                "File_pub": 0.8515732198421142
            }
        },
        {
            "Step": 8,
            "Action": "Toggle",
            "FMMFSM Task Labels": {
                "File_pri": 0.8285139808745624,
                "File_pub": 0.8488036638101311
            }
        },
        {
            "Step": 9,
            "Action": "Toggle",
            "FMMFSM Task Labels": {
                "File_pri": 0.8266665023768086,
                "File_pub": 0.8460234180127035
            }
        },
        {
            "Step": 10,
            "Action": "Select_folder",
            "FMMFSM Task Labels": {
                "File_pri": 0.8247676388950184,
                "File_pub": 0.8432776850777355
            }
        },
        {
            "Step": 11,
            "Action": "Select_folder",
            "FMMFSM Task Labels": {
                "Folder_pri": 0.8117438086899346,
                "Folder_pub": 0.8166034528692228
            }
        },
        {
            "Step": 12,
            "Action": "Select_folder",
            "FMMFSM Task Labels": {
                "Folder_pri": 0.8613523458519767,
                "Folder_pub": 0.8640288337497914,
                "File_pri": 0.7099260922304891,
                "File_pub": 0.7125701853082069
            }
        },
        {
            "Step": 13,
            "Action": "Toggle",
            "FMMFSM Task Labels": {
                "Folder_pri": 0.8840907549600171,
                "Folder_pub": 0.885444540795756,
                "File_pri": 0.7313388976306321,
                "File_pub": 0.7327220782197867
            }
        },
        {
            "Step": 14,
            "Action": "Toggle",
            "FMMFSM Task Labels": {
                "Folder_pri": 0.813628236380874,
                "Folder_pub": 0.8125962514704597,
                "File_pri": 0.7358400091979527,
                "File_pub": 0.7371552907760188
            }
        },
        {
            "Step": 15,
            "Action": "Toggle",
            "FMMFSM Task Labels": {
                "Folder_pri": 0.7542729260052357,
                "Folder_pub": 0.7550645974287973,
                "File_pri": 0.7395523641531904,
                "File_pub": 0.7407991413983162
            }
        },
        {
            "Step": 16,
            "Action": "Toggle",
            "FMMFSM Task Labels": {
                "Folder_pri": 0.7065878944786766,
                "Folder_pub": 0.7059867068693084,
                "File_pri": 0.742627170030226,
                "File_pub": 0.743816035342971
            }
        },
        {
            "Step": 17,
            "Action": "Toggle",
            "FMMFSM Task Labels": {
                "File_pri": 0.7451870808784016,
                "File_pub": 0.7463185872252807
            }
        },
        {
            "Step": 18,
            "Action": "Toggle",
            "FMMFSM Task Labels": {
                "File_pri": 0.7473193430530573,
                "File_pub": 0.7484004016926721
            }
        },
        {
            "Step": 19,
            "Action": "Toggle",
            "FMMFSM Task Labels": {
                "File_pri": 0.749097806152774,
                "File_pub": 0.7501295578323768
            }
        },
        {
            "Step": 20,
            "Action": null,
            "FMMFSM Task Labels": {
                "File_pri": 0.750577296147985,
                "File_pub": 0.7515644860268503
            }
        }
    ],
    "Threshold Nondeterministic Task Confusion": [
        {
            "Step": 2,
            "Action": "Select_file",
            "FMMFSM Task Labels": {
                "Secure": 0.7666099710273246,
                "Insecure": 0.8170048051531932
            }
        },
        {
            "Step": 3,
            "Action": "Select_file",
            "FMMFSM Task Labels": {
                "Secure": 0.8475790116259916,
                "Insecure": 0.8780670981710257
            }
        },
        {
            "Step": 4,
            "Action": "Select_file",
            "FMMFSM Task Labels": {
                "Secure": 0.8973823186606311,
                "Insecure": 0.9146220572826451
            }
        },
        {
            "Step": 5,
            "Action": "Toggle",
            "FMMFSM Task Labels": {
                "Secure": 0.924730490128133,
                "Insecure": 0.9336890624599441
            }
        },
        {
            "Step": 6,
            "Action": "Toggle",
            "FMMFSM Task Labels": {
                "Secure": 0.9213730957502041,
                "Insecure": 0.9249713095162385
            }
        },
        {
            "Step": 7,
            "Action": "Toggle",
            "FMMFSM Task Labels": {
                "Secure": 0.9136285417645523,
                "Insecure": 0.9215363267673725
            }
        },
        {
            "Step": 8,
            "Action": "Toggle",
            "FMMFSM Task Labels": {
                "Secure": 0.9103346081006477,
                "Insecure": 0.9150052631430312
            }
        },
        {
            "Step": 9,
            "Action": "Toggle",
            "FMMFSM Task Labels": {
                "Secure": 0.9045446094752706,
                "Insecure": 0.9116857890513647
            }
        },
        {
            "Step": 10,
            "Action": "Select_folder",
            "FMMFSM Task Labels": {
                "Secure": 0.9014499360197087,
                "Insecure": 0.9066065898669708
            }
        },
        {
            "Step": 11,
            "Action": "Select_folder",
            "FMMFSM Task Labels": {
                "Secure": 0.9247735460100924,
                "Insecure": 0.9266501803165914
            }
        },
        {
            "Step": 12,
            "Action": "Select_folder",
            "FMMFSM Task Labels": {
                "Secure": 0.9424314909178784,
                "Insecure": 0.9433522376630478
            }
        },
        {
            "Step": 13,
            "Action": "Toggle",
            "FMMFSM Task Labels": {
                "Secure": 0.9509536327249679,
                "Insecure": 0.9513919447356223
            }
        },
        {
            "Step": 14,
            "Action": "Toggle",
            "FMMFSM Task Labels": {
                "Secure": 0.9354351045859277,
                "Insecure": 0.9354341986865551
            }
        },
        {
            "Step": 15,
            "Action": "Toggle",
            "FMMFSM Task Labels": {
                "Secure": 0.9223318378285756,
                "Insecure": 0.9227271726534656
            }
        },
        {
            "Step": 16,
            "Action": "Toggle",
            "FMMFSM Task Labels": {
                "Secure": 0.911734537037745,
                "Insecure": 0.9118762880576402
            }
        },
        {
            "Step": 17,
            "Action": "Toggle",
            "FMMFSM Task Labels": {
                "Secure": 0.9026063954978266,
                "Insecure": 0.9029723015461271
            }
        },
        {
            "Step": 18,
            "Action": "Toggle",
            "FMMFSM Task Labels": {
                "Secure": 0.8950245540220427,
                "Insecure": 0.8952419406701623
            }
        },
        {
            "Step": 19,
            "Action": "Toggle",
            "FMMFSM Task Labels": {
                "Secure": 0.8884024853851433,
                "Insecure": 0.888745970255159
            }
        },
        {
            "Step": 20,
            "Action": null,
            "FMMFSM Task Labels": {
                "Secure": 0.8827843713113268,
                "Insecure": 0.8830391142710994
            }
        }
    ]
}